{"ast":null,"code":"jQuery(document).ready(function ($) {\n  // =========== navigation animation ============//\n  jQuery(\".navi-icon\").click(function () {\n    jQuery(this).toggleClass('open');\n    jQuery(\".navigation-holder\").slideToggle();\n  });\n  jQuery(\"ul.navigation li a\").click(function () {\n    jQuery(\".navi-icon\").removeClass(\"open\");\n\n    if (jQuery(window).width() < 1000) {\n      jQuery(\".navigation-holder\").slideUp();\n    }\n  });\n});","map":{"version":3,"sources":["/Users/arkhitech/work/cefiles-prod/app/javascript/packs/home.js"],"names":["jQuery","document","ready","$","click","toggleClass","slideToggle","removeClass","window","width","slideUp"],"mappings":"AAAAA,MAAM,CAACC,QAAD,CAAN,CAAiBC,KAAjB,CAAuB,UAASC,CAAT,EAAW;AAE9B;AACAH,EAAAA,MAAM,CAAC,YAAD,CAAN,CAAqBI,KAArB,CAA2B,YAAY;AACnCJ,IAAAA,MAAM,CAAC,IAAD,CAAN,CAAaK,WAAb,CAAyB,MAAzB;AACAL,IAAAA,MAAM,CAAC,oBAAD,CAAN,CAA6BM,WAA7B;AACH,GAHD;AAIAN,EAAAA,MAAM,CAAC,oBAAD,CAAN,CAA6BI,KAA7B,CAAmC,YAAY;AAC3CJ,IAAAA,MAAM,CAAC,YAAD,CAAN,CAAqBO,WAArB,CAAiC,MAAjC;;AACA,QAAGP,MAAM,CAACQ,MAAD,CAAN,CAAeC,KAAf,KAAyB,IAA5B,EAAiC;AAC7BT,MAAAA,MAAM,CAAC,oBAAD,CAAN,CAA6BU,OAA7B;AACH;AACJ,GALD;AASH,CAhBD","sourcesContent":["jQuery(document).ready(function($){\n\n    // =========== navigation animation ============//\n    jQuery(\".navi-icon\").click(function () {\n        jQuery(this).toggleClass('open');\n        jQuery(\".navigation-holder\").slideToggle();\n    });\n    jQuery(\"ul.navigation li a\").click(function () {\n        jQuery(\".navi-icon\").removeClass(\"open\");\n        if(jQuery(window).width() < 1000){\n            jQuery(\".navigation-holder\").slideUp();\n        }\n    });\n\n\n\n});\n"]},"metadata":{},"sourceType":"module"}